greenhub/__init__.py
greenhub/data.py
greenhub/initialize.py
greenhub/scripts/__init__.py
greenhub/utilities/__init__.py
greenhub/utilities/auth.py
greenhub/utilities/feature_data_cache.py
greenhub/utilities/feature_data_renamings.py
greenhub-1.0.9.dist-info/METADATA
greenhub-1.0.9.dist-info/WHEEL
greenhub-1.0.9.dist-info/entry_points.txt
greenhub-1.0.9.dist-info/licenses/LICENSE
greenhub-1.0.9.dist-info/RECORD
