Metadata-Version: 2.4
Name: greenhub
Version: 1.0.9
Summary: Python toolbox for the greenhub.ai platform, offering capabilities for data access, model creation, and deployment.
Project-URL: Homepage, https://greenhub.ai
Project-URL: Wiki, https://docs.greenhub.ai
Author-email: Linus Sander <linus.sander@tum.de>, Jonas Engesser <info@greenhub.ai>, Florian Schmidt <info@greenhub.ai>, Christoph Starnecker <info@greenhub.ai>, Malte von Bloh <info@greenhub.ai>, Maximilian Zachow <info@greenhub.ai>
License: Copyright (c) 2024 greenhub.ai
License-File: LICENSE
Classifier: License :: OSI Approved :: MIT License
Classifier: Operating System :: OS Independent
Classifier: Programming Language :: Python :: 3
Requires-Python: >=3.1
Requires-Dist: pandas>=2.0.1
Requires-Dist: requests>=2.20.1
Requires-Dist: tqdm>=4.20.1
